vocab_builder/__init__.py
vocab_builder/__main__.py
vocab_builder/base.py
vocab_builder/char.py
vocab_builder/char_word.py
vocab_builder/vocab.py
vocab_builder/word.py
vocab_builder-0.0.1a2.dist-info/DESCRIPTION.rst
vocab_builder-0.0.1a2.dist-info/METADATA
vocab_builder-0.0.1a2.dist-info/RECORD
vocab_builder-0.0.1a2.dist-info/WHEEL
vocab_builder-0.0.1a2.dist-info/entry_points.txt
vocab_builder-0.0.1a2.dist-info/metadata.json
vocab_builder-0.0.1a2.dist-info/top_level.txt
