Metadata-Version: 2.0
Name: vocab-builder
Version: 0.0.1a2
Summary: Common NLP vocab builder and class
Home-page: https://github.com/codertimo/vocab-builder
Author: Junseong Kim
Author-email: codertimo@gmail.com
License: UNKNOWN
Platform: UNKNOWN
Classifier: Programming Language :: Python :: 3
Classifier: License :: OSI Approved :: Apache Software License
Classifier: Operating System :: OS Independent
Requires-Dist: tqdm
